Workbook

Sheet Data
A1: Month | B1: MonthNo | C1: Department | D1: Region | E1: TargetOrders | F1: DeliveredOrders | G1: OnTimeOrders | H1: Revenue | I1: COGS | J1: OpCost | K1: DeliveryDaysTotal | L1: DefectOrders | N1: SAMPLE DATA - made up for portfolio demo
A2: 46047 | B2: 1 | C2: Logistics | D2: North | E2: 476 | F2: 434 | G2: 365 | H2: 101556 | I2: 65199 | J2: 12085 | K2: 2126.6 | L2: 22
A3: 46047 | B3: 1 | C3: Logistics | D3: South | E3: 547 | F3: 495 | G3: 448 | H3: 115830 | I3: 79807 | J3: 13668 | K3: 2029.5 | L3: 21
A4: 46047 | B4: 1 | C4: Logistics | D4: East | E4: 543 | F4: 564 | G4: 482 | H4: 122952 | I4: 87050 | J4: 13648 | K4: 2368.8 | L4: 27
A5: 46047 | B5: 1 | C5: Logistics | D5: West | E5: 552 | F5: 530 | G5: 480 | H5: 121900 | I5: 79844 | J5: 13775 | K5: 2491 | L5: 19
A6: 46047 | B6: 1 | C6: Operations | D6: North | E6: 451 | F6: 449 | G6: 361 | H6: 86208 | I6: 62673 | J6: 9138 | K6: 1840.9 | L6: 21
A7: 46047 | B7: 1 | C7: Operations | D7: South | E7: 416 | F7: 376 | G7: 314 | H7: 75200 | I7: 49106 | J7: 9701 | K7: 1767.2 | L7: 16
A8: 46047 | B8: 1 | C8: Operations | D8: East | E8: 391 | F8: 328 | G8: 311 | H8: 62320 | I8: 40321 | J8: 9784 | K8: 1508.8 | L8: 12
A9: 46047 | B9: 1 | C9: Operations | D9: West | E9: 444 | F9: 430 | G9: 349 | H9: 86860 | I9: 60802 | J9: 12942 | K9: 2107 | L9: 22
A10: 46047 | B10: 1 | C10: Supply Chain | D10: North | E10: 461 | F10: 477 | G10: 422 | H10: 100647 | I10: 65622 | J10: 10769 | K10: 2003.4 | L10: 23
A11: 46047 | B11: 1 | C11: Supply Chain | D11: South | E11: 383 | F11: 388 | G11: 359 | H11: 79152 | I11: 56356 | J11: 8390 | K11: 1629.6 | L11: 21
A12: 46047 | B12: 1 | C12: Supply Chain | D12: East | E12: 458 | F12: 395 | G12: 321 | H12: 84530 | I12: 58664 | J12: 12764 | K12: 1698.5 | L12: 16
A13: 46047 | B13: 1 | C13: Supply Chain | D13: West | E13: 447 | F13: 395 | G13: 334 | H13: 90455 | I13: 62143 | J13: 14111 | K13: 1935.5 | L13: 21
... A145: 46381 | B145: 12 | C145: Supply Chain | D145: West | E145: 554 | F145: 540 | G145: 465 | H145: 122040 | I145: 78716 | J145: 15987 | K145: 2073.6 | L145: 14

Sheet Dashboard
B1: OPERATIONS & LOGISTICS MIS REPORT | SAMPLE DATA | V1: DeptCrit | W1: =IF($D$5="All","*",$D$5) -> * | X1: Month | Y1: Target Orders | Z1: Delivered Orders | AA1: SLA Compliance % | AB1: Margin % | AC1: Gross Profit | AD1: Operational Cost | AE1: Defect Rate % | AG1: Region | AH1: Delivered Orders | AJ1: DeptList | AL1: RegList
V2: RegCrit | W2: =IF($J$5="All","*",$J$5) -> * | X2: 46047 | Y2: =SUMIFS(Data!$E$2:$E$145,Data!$B$2:$B$145,1,Data!$C$2:$C$145,$W$1,Data!$D$2:$D$145,$W$2) -> 5569 | Z2: =SUMIFS(Data!$F$2:$F$145,Data!$B$2:$B$145,1,Data!$C$2:$C$145,$W$1,Data!$D$2:$D$145,$W$2) -> 5261 | AA2: =IFERROR(SUMIFS(Data!$G$2:$G$145,Data!$B$2:$B$145,1,Data!$C$2:$C$145,$W$1,Data!$D$2:$D$145,$W$2)/Z2,0) -> 0.86409428 | AB2: =IFERROR((SUMIFS(Data!$H$2:$H$145,Data!$B$2:$B$145,1,Data!$C$2:$C$145,$W$1,Data!$D$2:$D$145,$W$2)-SUMIFS(Data!$I$2:$I$145,Data!$B$2:$B$145,1,Data!$C$2:$C$145,$W$1,Data!$D$2:$D$145,$W$2))/SUMIFS(Data!$H$2:$H$145,Data!$B$2:$B$145,1,Data!$C$2:$C$145,$W$1,Data!$D$2:$D$145,$W$2),0) -> 0.31927972 | AC2: =SUMIFS(Data!$H$2:$H$145,Data!$B$2:$B$145,1,Data!$C$2:$C$145,$W$1,Data!$D$2:$D$145,$W$2)-SUMIFS(Data!$I$2:$I$145,Data!$B$2:$B$145,1,Data!$C$2:$C$145,$W$1,Data!$D$2:$D$145,$W$2) -> 360023 | AD2: =SUMIFS(Data!$J$2:$J$145,Data!$B$2:$B$145,1,Data!$C$2:$C$145,$W$1,Data!$D$2:$D$145,$W$2) -> 140775 | AE2: =IFERROR(SUMIFS(Data!$L$2:$L$145,Data!$B$2:$B$145,1,Data!$C$2:$C$145,$W$1,Data!$D$2:$D$145,$W$2)/Z2,0) -> 0.045808782 | AG2: North | AH2: =IF(OR($J$5="All",$J$5=AG2),SUMIFS(Data!$F$2:$F$145,Data!$D$2:$D$145,AG2,Data!$C$2:$C$145,$W$1),0) -> 16880 | AJ2: All | AL2: All
X3: 46078 | Y3: =SUMIFS(Data!$E$2:$E$145,Data!$B$2:$B$145,2,Data!$C$2:$C$145,$W$1,Data!$D$2:$D$145,$W$2) -> 5652 | Z3: =SUMIFS(Data!$F$2:$F$145,Data!$B$2:$B$145,2,Data!$C$2:$C$145,$W$1,Data!$D$2:$D$145,$W$2) -> 5177 | AA3: =IFERROR(SUMIFS(Data!$G$2:$G$145,Data!$B$2:$B$145,2,Data!$C$2:$C$145,$W$1,Data!$D$2:$D$145,$W$2)/Z3,0) -> 0.85976434 | AB3: =IFERROR((SUMIFS(Data!$H$2:$H$145,Data!$B$2:$B$145,2,Data!$C$2:$C$145,$W$1,Data!$D$2:$D$145,$W$2)-SUMIFS(Data!$I$2:$I$145,Data!$B$2:$B$145,2,Data!$C$2:$C$145,$W$1,Data!$D$2:$D$145,$W$2))/SUMIFS(Data!$H$2:$H$145,Data!$B$2:$B$145,2,Data!$C$2:$C$145,$W$1,Data!$D$2:$D$145,$W$2),0) -> 0.31193437 | AC3: =SUMIFS(Data!$H$2:$H$145,Data!$B$2:$B$145,2,Data!$C$2:$C$145,$W$1,Data!$D$2:$D$145,$W$2)-SUMIFS(Data!$I$2:$I$145,Data!$B$2:$B$145,2,Data!$C$2:$C$145,$W$1,Data!$D$2:$D$145,$W$2) -> 346983 | AD3: =SUMIFS(Data!$J$2:$J$145,Data!$B$2:$B$145,2,Data!$C$2:$C$145,$W$1,Data!$D$2:$D$145,$W$2) -> 143823 | AE3: =IFERROR(SUMIFS(Data!$L$2:$L$145,Data!$B$2:$B$145,2,Data!$C$2:$C$145,$W$1,Data!$D$2:$D$145,$W$2)/Z3,0) -> 0.045586247 | AG3: South | AH3: =IF(OR($J$5="All",$J$5=AG3),SUMIFS(Data!$F$2:$F$145,Data!$D$2:$D$145,AG3,Data!$C$2:$C$145,$W$1),0) -> 16833 | AJ3: Logistics | AL3: North
X4: 46106 | Y4: =SUMIFS(Data!$E$2:$E$145,Data!$B$2:$B$145,3,Data!$C$2:$C$145,$W$1,Data!$D$2:$D$145,$W$2) -> 5588 | Z4: =SUMIFS(Data!$F$2:$F$145,Data!$B$2:$B$145,3,Data!$C$2:$C$145,$W$1,Data!$D$2:$D$145,$W$2) -> 5127 | AA4: =IFERROR(SUMIFS(Data!$G$2:$G$145,Data!$B$2:$B$145,3,Data!$C$2:$C$145,$W$1,Data!$D$2:$D$145,$W$2)/Z4,0) -> 0.88433782 | AB4: =IFERROR((SUMIFS(Data!$H$2:$H$145,Data!$B$2:$B$145,3,Data!$C$2:$C$145,$W$1,Data!$D$2:$D$145,$W$2)-SUMIFS(Data!$I$2:$I$145,Data!$B$2:$B$145,3,Data!$C$2:$C$145,$W$1,Data!$D$2:$D$145,$W$2))/SUMIFS(Data!$H$2:$H$145,Data!$B$2:$B$145,3,Data!$C$2:$C$145,$W$1,Data!$D$2:$D$145,$W$2),0) -> 0.33330588 | AC4: =SUMIFS(Data!$H$2:$H$145,Data!$B$2:$B$145,3,Data!$C$2:$C$145,$W$1,Data!$D$2:$D$145,$W$2)-SUMIFS(Data!$I$2:$I$145,Data!$B$2:$B$145,3,Data!$C$2:$C$145,$W$1,Data!$D$2:$D$145,$W$2) -> 380465 | AD4: =SUMIFS(Data!$J$2:$J$145,Data!$B$2:$B$145,3,Data!$C$2:$C$145,$W$1,Data!$D$2:$D$145,$W$2) -> 152548 | AE4: =IFERROR(SUMIFS(Data!$L$2:$L$145,Data!$B$2:$B$145,3,Data!$C$2:$C$145,$W$1,Data!$D$2:$D$145,$W$2)/Z4,0) -> 0.041739809 | AG4: East | AH4: =IF(OR($J$5="All",$J$5=AG4),SUMIFS(Data!$F$2:$F$145,Data!$D$2:$D$145,AG4,Data!$C$2:$C$145,$W$1),0) -> 17203 | AJ4: Operations | AL4: South
B5: Department | D5: All | H5: Region | J5: All | N5: << pick Department / Region, whole report updates | X5: 46137 | Y5: =SUMIFS(Data!$E$2:$E$145,Data!$B$2:$B$145,4,Data!$C$2:$C$145,$W$1,Data!$D$2:$D$145,$W$2) -> 5915 | Z5: =SUMIFS(Data!$F$2:$F$145,Data!$B$2:$B$145,4,Data!$C$2:$C$145,$W$1,Data!$D$2:$D$145,$W$2) -> 5611 | AA5: =IFERROR(SUMIFS(Data!$G$2:$G$145,Data!$B$2:$B$145,4,Data!$C$2:$C$145,$W$1,Data!$D$2:$D$145,$W$2)/Z5,0) -> 0.89413652 | AB5: =IFERROR((SUMIFS(Data!$H$2:$H$145,Data!$B$2:$B$145,4,Data!$C$2:$C$145,$W$1,Data!$D$2:$D$145,$W$2)-SUMIFS(Data!$I$2:$I$145,Data!$B$2:$B$145,4,Data!$C$2:$C$145,$W$1,Data!$D$2:$D$145,$W$2))/SUMIFS(Data!$H$2:$H$145,Data!$B$2:$B$145,4,Data!$C$2:$C$145,$W$1,Data!$D$2:$D$145,$W$2),0) -> 0.31723921 | AC5: =SUMIFS(Data!$H$2:$H$145,Data!$B$2:$B$145,4,Data!$C$2:$C$145,$W$1,Data!$D$2:$D$145,$W$2)-SUMIFS(Data!$I$2:$I$145,Data!$B$2:$B$145,4,Data!$C$2:$C$145,$W$1,Data!$D$2:$D$145,$W$2) -> 379663 | AD5: =SUMIFS(Data!$J$2:$J$145,Data!$B$2:$B$145,4,Data!$C$2:$C$145,$W$1,Data!$D$2:$D$145,$W$2) -> 151129 | AE5: =IFERROR(SUMIFS(Data!$L$2:$L$145,Data!$B$2:$B$145,4,Data!$C$2:$C$145,$W$1,Data!$D$2:$D$145,$W$2)/Z5,0) -> 0.041525575 | AG5: West | AH5: =IF(OR($J$5="All",$J$5=AG5),SUMIFS(Data!$F$2:$F$145,Data!$D$2:$D$145,AG5,Data!$C$2:$C$145,$W$1),0) -> 18580 | AJ5: Supply Chain | AL5: East
X6: 46167 | Y6: =SUMIFS(Data!$E$2:$E$145,Data!$B$2:$B$145,5,Data!$C$2:$C$145,$W$1,Data!$D$2:$D$145,$W$2) -> 5912 | Z6: =SUMIFS(Data!$F$2:$F$145,Data!$B$2:$B$145,5,Data!$C$2:$C$145,$W$1,Data!$D$2:$D$145,$W$2) -> 5577 | AA6: =IFERROR(SUMIFS(Data!$G$2:$G$145,Data!$B$2:$B$145,5,Data!$C$2:$C$145,$W$1,Data!$D$2:$D$145,$W$2)/Z6,0) -> 0.87860857 | AB6: =IFERROR((SUMIFS(Data!$H$2:$H$145,Data!$B$2:$B$145,5,Data!$C$2:$C$145,$W$1,Data!$D$2:$D$145,$W$2)-SUMIFS(Data!$I$2:$I$145,Data!$B$2:$B$145,5,Data!$C$2:$C$145,$W$1,Data!$D$2:$D$145,$W$2))/SUMIFS(Data!$H$2:$H$145,Data!$B$2:$B$145,5,Data!$C$2:$C$145,$W$1,Data!$D$2:$D$145,$W$2),0) -> 0.32282353 | AC6: =SUMIFS(Data!$H$2:$H$145,Data!$B$2:$B$145,5,Data!$C$2:$C$145,$W$1,Data!$D$2:$D$145,$W$2)-SUMIFS(Data!$I$2:$I$145,Data!$B$2:$B$145,5,Data!$C$2:$C$145,$W$1,Data!$D$2:$D$145,$W$2) -> 375580 | AD6: =SUMIFS(Data!$J$2:$J$145,Data!$B$2:$B$145,5,Data!$C$2:$C$145,$W$1,Data!$D$2:$D$145,$W$2) -> 140169 | AE6: =IFERROR(SUMIFS(Data!$L$2:$L$145,Data!$B$2:$B$145,5,Data!$C$2:$C$145,$W$1,Data!$D$2:$D$145,$W$2)/Z6,0) -> 0.039447732 | AL6: West
B7: Gross Profit | G7: Margin % | L7: Delivered Orders | Q7: Order Achievement % | X7: 46198 | Y7: =SUMIFS(Data!$E$2:$E$145,Data!$B$2:$B$145,6,Data!$C$2:$C$145,$W$1,Data!$D$2:$D$145,$W$2) -> 5965 | Z7: =SUMIFS(Data!$F$2:$F$145,Data!$B$2:$B$145,6,Data!$C$2:$C$145,$W$1,Data!$D$2:$D$145,$W$2) -> 5672 | AA7: =IFERROR(SUMIFS(Data!$G$2:$G$145,Data!$B$2:$B$145,6,Data!$C$2:$C$145,$W$1,Data!$D$2:$D$145,$W$2)/Z7,0) -> 0.88945698 | AB7: =IFERROR((SUMIFS(Data!$H$2:$H$145,Data!$B$2:$B$145,6,Data!$C$2:$C$145,$W$1,Data!$D$2:$D$145,$W$2)-SUMIFS(Data!$I$2:$I$145,Data!$B$2:$B$145,6,Data!$C$2:$C$145,$W$1,Data!$D$2:$D$145,$W$2))/SUMIFS(Data!$H$2:$H$145,Data!$B$2:$B$145,6,Data!$C$2:$C$145,$W$1,Data!$D$2:$D$145,$W$2),0) -> 0.32397139 | AC7: =SUMIFS(Data!$H$2:$H$145,Data!$B$2:$B$145,6,Data!$C$2:$C$145,$W$1,Data!$D$2:$D$145,$W$2)-SUMIFS(Data!$I$2:$I$145,Data!$B$2:$B$145,6,Data!$C$2:$C$145,$W$1,Data!$D$2:$D$145,$W$2) -> 389227 | AD7: =SUMIFS(Data!$J$2:$J$145,Data!$B$2:$B$145,6,Data!$C$2:$C$145,$W$1,Data!$D$2:$D$145,$W$2) -> 169213 | AE7: =IFERROR(SUMIFS(Data!$L$2:$L$145,Data!$B$2:$B$145,6,Data!$C$2:$C$145,$W$1,Data!$D$2:$D$145,$W$2)/Z7,0) -> 0.035084626
B8: =SUM($AC$2:$AC$13) -> 4762625 | G8: =IFERROR(SUM($AC$2:$AC$13)/SUMIFS(Data!$H$2:$H$145,Data!$C$2:$C$145,$W$1,Data!$D$2:$D$145,$W$2),0) -> 0.31992857 | L8: =SUM($Z$2:$Z$13) -> 69496 | Q8: =IFERROR(SUM($Z$2:$Z$13)/SUM($Y$2:$Y$13),0) -> 0.94911365 | X8: 46228 | Y8: =SUMIFS(Data!$E$2:$E$145,Data!$B$2:$B$145,7,Data!$C$2:$C$145,$W$1,Data!$D$2:$D$145,$W$2) -> 6170 | Z8: =SUMIFS(Data!$F$2:$F$145,Data!$B$2:$B$145,7,Data!$C$2:$C$145,$W$1,Data!$D$2:$D$145,$W$2) -> 5978 | AA8: =IFERROR(SUMIFS(Data!$G$2:$G$145,Data!$B$2:$B$145,7,Data!$C$2:$C$145,$W$1,Data!$D$2:$D$145,$W$2)/Z8,0) -> 0.91217799 | AB8: =IFERROR((SUMIFS(Data!$H$2:$H$145,Data!$B$2:$B$145,7,Data!$C$2:$C$145,$W$1,Data!$D$2:$D$145,$W$2)-SUMIFS(Data!$I$2:$I$145,Data!$B$2:$B$145,7,Data!$C$2:$C$145,$W$1,Data!$D$2:$D$145,$W$2))/SUMIFS(Data!$H$2:$H$145,Data!$B$2:$B$145,7,Data!$C$2:$C$145,$W$1,Data!$D$2:$D$145,$W$2),0) -> 0.31003876 | AC8: =SUMIFS(Data!$H$2:$H$145,Data!$B$2:$B$145,7,Data!$C$2:$C$145,$W$1,Data!$D$2:$D$145,$W$2)-SUMIFS(Data!$I$2:$I$145,Data!$B$2:$B$145,7,Data!$C$2:$C$145,$W$1,Data!$D$2:$D$145,$W$2) -> 386463 | AD8: =SUMIFS(Data!$J$2:$J$145,Data!$B$2:$B$145,7,Data!$C$2:$C$145,$W$1,Data!$D$2:$D$145,$W$2) -> 161375 | AE8: =IFERROR(SUMIFS(Data!$L$2:$L$145,Data!$B$2:$B$145,7,Data!$C$2:$C$145,$W$1,Data!$D$2:$D$145,$W$2)/Z8,0) -> 0.039143526
X9: 46259 | Y9: =SUMIFS(Data!$E$2:$E$145,Data!$B$2:$B$145,8,Data!$C$2:$C$145,$W$1,Data!$D$2:$D$145,$W$2) -> 6392 | Z9: =SUMIFS(Data!$F$2:$F$145,Data!$B$2:$B$145,8,Data!$C$2:$C$145,$W$1,Data!$D$2:$D$145,$W$2) -> 6003 | AA9: =IFERROR(SUMIFS(Data!$G$2:$G$145,Data!$B$2:$B$145,8,Data!$C$2:$C$145,$W$1,Data!$D$2:$D$145,$W$2)/Z9,0) -> 0.89355322 | AB9: =IFERROR((SUMIFS(Data!$H$2:$H$145,Data!$B$2:$B$145,8,Data!$C$2:$C$145,$W$1,Data!$D$2:$D$145,$W$2)-SUMIFS(Data!$I$2:$I$145,Data!$B$2:$B$145,8,Data!$C$2:$C$145,$W$1,Data!$D$2:$D$145,$W$2))/SUMIFS(Data!$H$2:$H$145,Data!$B$2:$B$145,8,Data!$C$2:$C$145,$W$1,Data!$D$2:$D$145,$W$2),0) -> 0.31580984 | AC9: =SUMIFS(Data!$H$2:$H$145,Data!$B$2:$B$145,8,Data!$C$2:$C$145,$W$1,Data!$D$2:$D$145,$W$2)-SUMIFS(Data!$I$2:$I$145,Data!$B$2:$B$145,8,Data!$C$2:$C$145,$W$1,Data!$D$2:$D$145,$W$2) -> 403160 | AD9: =SUMIFS(Data!$J$2:$J$145,Data!$B$2:$B$145,8,Data!$C$2:$C$145,$W$1,Data!$D$2:$D$145,$W$2) -> 162173 | AE9: =IFERROR(SUMIFS(Data!$L$2:$L$145,Data!$B$2:$B$145,8,Data!$C$2:$C$145,$W$1,Data!$D$2:$D$145,$W$2)/Z9,0) -> 0.035149092
X10: 46290 | Y10: =SUMIFS(Data!$E$2:$E$145,Data!$B$2:$B$145,9,Data!$C$2:$C$145,$W$1,Data!$D$2:$D$145,$W$2) -> 6176 | Z10: =SUMIFS(Data!$F$2:$F$145,Data!$B$2:$B$145,9,Data!$C$2:$C$145,$W$1,Data!$D$2:$D$145,$W$2) -> 5896 | AA10: =IFERROR(SUMIFS(Data!$G$2:$G$145,Data!$B$2:$B$145,9,Data!$C$2:$C$145,$W$1,Data!$D$2:$D$145,$W$2)/Z10,0) -> 0.88042741 | AB10: =IFERROR((SUMIFS(Data!$H$2:$H$145,Data!$B$2:$B$145,9,Data!$C$2:$C$145,$W$1,Data!$D$2:$D$145,$W$2)-SUMIFS(Data!$I$2:$I$145,Data!$B$2:$B$145,9,Data!$C$2:$C$145,$W$1,Data!$D$2:$D$145,$W$2))/SUMIFS(Data!$H$2:$H$145,Data!$B$2:$B$145,9,Data!$C$2:$C$145,$W$1,Data!$D$2:$D$145,$W$2),0) -> 0.31886834 | AC10: =SUMIFS(Data!$H$2:$H$145,Data!$B$2:$B$145,9,Data!$C$2:$C$145,$W$1,Data!$D$2:$D$145,$W$2)-SUMIFS(Data!$I$2:$I$145,Data!$B$2:$B$145,9,Data!$C$2:$C$145,$W$1,Data!$D$2:$D$145,$W$2) -> 403224 | AD10: =SUMIFS(Data!$J$2:$J$145,Data!$B$2:$B$145,9,Data!$C$2:$C$145,$W$1,Data!$D$2:$D$145,$W$2) -> 166588 | AE10: =IFERROR(SUMIFS(Data!$L$2:$L$145,Data!$B$2:$B$145,9,Data!$C$2:$C$145,$W$1,Data!$D$2:$D$145,$W$2)/Z10,0) -> 0.034260516
B11: SLA Compliance % | G11: Avg Delivery Days | L11: Avg Defect Rate % | Q11: Operational Cost | X11: 46320 | Y11: =SUMIFS(Data!$E$2:$E$145,Data!$B$2:$B$145,10,Data!$C$2:$C$145,$W$1,Data!$D$2:$D$145,$W$2) -> 6558 | Z11: =SUMIFS(Data!$F$2:$F$145,Data!$B$2:$B$145,10,Data!$C$2:$C$145,$W$1,Data!$D$2:$D$145,$W$2) -> 6245 | AA11: =IFERROR(SUMIFS(Data!$G$2:$G$145,Data!$B$2:$B$145,10,Data!$C$2:$C$145,$W$1,Data!$D$2:$D$145,$W$2)/Z11,0) -> 0.91833467 | AB11: =IFERROR((SUMIFS(Data!$H$2:$H$145,Data!$B$2:$B$145,10,Data!$C$2:$C$145,$W$1,Data!$D$2:$D$145,$W$2)-SUMIFS(Data!$I$2:$I$145,Data!$B$2:$B$145,10,Data!$C$2:$C$145,$W$1,Data!$D$2:$D$145,$W$2))/SUMIFS(Data!$H$2:$H$145,Data!$B$2:$B$145,10,Data!$C$2:$C$145,$W$1,Data!$D$2:$D$145,$W$2),0) -> 0.32814095 | AC11: =SUMIFS(Data!$H$2:$H$145,Data!$B$2:$B$145,10,Data!$C$2:$C$145,$W$1,Data!$D$2:$D$145,$W$2)-SUMIFS(Data!$I$2:$I$145,Data!$B$2:$B$145,10,Data!$C$2:$C$145,$W$1,Data!$D$2:$D$145,$W$2) -> 436752 | AD11: =SUMIFS(Data!$J$2:$J$145,Data!$B$2:$B$145,10,Data!$C$2:$C$145,$W$1,Data!$D$2:$D$145,$W$2) -> 170748 | AE11: =IFERROR(SUMIFS(Data!$L$2:$L$145,Data!$B$2:$B$145,10,Data!$C$2:$C$145,$W$1,Data!$D$2:$D$145,$W$2)/Z11,0) -> 0.032185749
B12: =IFERROR(SUMIFS(Data!$G$2:$G$145,Data!$C$2:$C$145,$W$1,Data!$D$2:$D$145,$W$2)/SUM($Z$2:$Z$13),0) -> 0.88900081 | G12: =IFERROR(SUMIFS(Data!$K$2:$K$145,Data!$C$2:$C$145,$W$1,Data!$D$2:$D$145,$W$2)/SUM($Z$2:$Z$13),0) -> 4.2355488 | L12: =IFERROR(SUMIFS(Data!$L$2:$L$145,Data!$C$2:$C$145,$W$1,Data!$D$2:$D$145,$W$2)/SUM($Z$2:$Z$13),0) -> 0.037426614 | Q12: =SUM($AD$2:$AD$13) -> 1935592 | X12: 46351 | Y12: =SUMIFS(Data!$E$2:$E$145,Data!$B$2:$B$145,11,Data!$C$2:$C$145,$W$1,Data!$D$2:$D$145,$W$2) -> 6586 | Z12: =SUMIFS(Data!$F$2:$F$145,Data!$B$2:$B$145,11,Data!$C$2:$C$145,$W$1,Data!$D$2:$D$145,$W$2) -> 6348 | AA12: =IFERROR(SUMIFS(Data!$G$2:$G$145,Data!$B$2:$B$145,11,Data!$C$2:$C$145,$W$1,Data!$D$2:$D$145,$W$2)/Z12,0) -> 0.88531821 | AB12: =IFERROR((SUMIFS(Data!$H$2:$H$145,Data!$B$2:$B$145,11,Data!$C$2:$C$145,$W$1,Data!$D$2:$D$145,$W$2)-SUMIFS(Data!$I$2:$I$145,Data!$B$2:$B$145,11,Data!$C$2:$C$145,$W$1,Data!$D$2:$D$145,$W$2))/SUMIFS(Data!$H$2:$H$145,Data!$B$2:$B$145,11,Data!$C$2:$C$145,$W$1,Data!$D$2:$D$145,$W$2),0) -> 0.31543774 | AC12: =SUMIFS(Data!$H$2:$H$145,Data!$B$2:$B$145,11,Data!$C$2:$C$145,$W$1,Data!$D$2:$D$145,$W$2)-SUMIFS(Data!$I$2:$I$145,Data!$B$2:$B$145,11,Data!$C$2:$C$145,$W$1,Data!$D$2:$D$145,$W$2) -> 431181 | AD12: =SUMIFS(Data!$J$2:$J$145,Data!$B$2:$B$145,11,Data!$C$2:$C$145,$W$1,Data!$D$2:$D$145,$W$2) -> 183158 | AE12: =IFERROR(SUMIFS(Data!$L$2:$L$145,Data!$B$2:$B$145,11,Data!$C$2:$C$145,$W$1,Data!$D$2:$D$145,$W$2)/Z12,0) -> 0.032451166
X13: 46381 | Y13: =SUMIFS(Data!$E$2:$E$145,Data!$B$2:$B$145,12,Data!$C$2:$C$145,$W$1,Data!$D$2:$D$145,$W$2) -> 6739 | Z13: =SUMIFS(Data!$F$2:$F$145,Data!$B$2:$B$145,12,Data!$C$2:$C$145,$W$1,Data!$D$2:$D$145,$W$2) -> 6601 | AA13: =IFERROR(SUMIFS(Data!$G$2:$G$145,Data!$B$2:$B$145,12,Data!$C$2:$C$145,$W$1,Data!$D$2:$D$145,$W$2)/Z13,0) -> 0.89774277 | AB13: =IFERROR((SUMIFS(Data!$H$2:$H$145,Data!$B$2:$B$145,12,Data!$C$2:$C$145,$W$1,Data!$D$2:$D$145,$W$2)-SUMIFS(Data!$I$2:$I$145,Data!$B$2:$B$145,12,Data!$C$2:$C$145,$W$1,Data!$D$2:$D$145,$W$2))/SUMIFS(Data!$H$2:$H$145,Data!$B$2:$B$145,12,Data!$C$2:$C$145,$W$1,Data!$D$2:$D$145,$W$2),0) -> 0.32231676 | AC13: =SUMIFS(Data!$H$2:$H$145,Data!$B$2:$B$145,12,Data!$C$2:$C$145,$W$1,Data!$D$2:$D$145,$W$2)-SUMIFS(Data!$I$2:$I$145,Data!$B$2:$B$145,12,Data!$C$2:$C$145,$W$1,Data!$D$2:$D$145,$W$2) -> 469904 | AD13: =SUMIFS(Data!$J$2:$J$145,Data!$B$2:$B$145,12,Data!$C$2:$C$145,$W$1,Data!$D$2:$D$145,$W$2) -> 193893 | AE13: =IFERROR(SUMIFS(Data!$L$2:$L$145,Data!$B$2:$B$145,12,Data!$C$2:$C$145,$W$1,Data!$D$2:$D$145,$W$2)/Z13,0) -> 0.030904408
B48: SAMPLE DATA: all numbers are made up for portfolio demonstration. Not real company data.
